besco/__init__.py
besco/azg.svg
besco/besco.py
besco/csv2turtle.py
besco/svg2csv.py
besco-0.0.7.dist-info/LICENSE.md
besco-0.0.7.dist-info/METADATA
besco-0.0.7.dist-info/WHEEL
besco-0.0.7.dist-info/entry_points.txt
besco-0.0.7.dist-info/top_level.txt
besco-0.0.7.dist-info/RECORD
