Metadata-Version: 2.1
Name: besco
Version: 0.0.7
Summary: Besco is not only a Python package, Besco is a way of life.
Home-page: https://github.com/SajjadAemmi/besco
Author: Sajjad Aemmi
Author-email: sajjadaemmi@gmail.com
License-File: LICENSE.md
Requires-Dist: svgpathtools
